{
  "text": "ยง 11-206 Power of the commissioner of finance to correct errors. The commissioner of finance may correct any assessment or tax which is erroneous due to a clerical error or to an error of description contained in the several books of annual record of assessed valuations, or in the assessments-rolls. If the taxes computed on such erroneous assessment have been paid, the commissioner of finance is authorized to refund or credit the difference between the taxes computed on the erroneous and corrected assessments. ",
  "sections": [

  ],
  "title": {
    "identifier": "11",
    "text": "TAXATION AND FINANCE"
  },
  "chapter": {
    "identifier": "2",
    "text": "REAL PROPERTY ASSESSMENT, TAXATION AND CHARGES"
  },
  "heading": {
    "title": "11",
    "chaptersection": "206",
    "identifier": "11-206",
    "catch_text": "Power of the commissioner of finance to correct errors."
  }
}