{
  "text": "ยง 17-308 Fees. a. The annual fees for licenses and permits set forth in subdivisions b and c of this section shall be payable at the time of application for a license or permit or renewal thereof, except as otherwise provided in subdivision e of section 17-307 of this subchapter. b. The annual fee for a license or renewal thereof shall be twenty-five dollars; provided, however, that for an initial license issued for more than two years the applicable license fee shall be increased proportionally to the nearest quarter year. c. The annual fee for a permit or renewal thereof shall be: 1. For a pushcart or vehicle selling prepackaged food or for a fresh fruits and vegetables permit: fifty dollars for the first year and twenty-five dollars for each year thereafter. 2. For a vehicle selling foods prepared or processed therein: one hundred dollars. d. The fee for issuing a duplicate license, permit or plate when the original has been lost, destroyed or mutilated shall be: ten dollars. e. A person holding a license pursuant to the provisions of article four of the general business law shall be exempt from the payment of fees set forth in this section. f. The fees provided for herein shall be in addition to any fees required pursuant to the New York city health code or the New York state sanitary code. ",
  "sections": [

  ],
  "title": {
    "identifier": "17",
    "text": "HEALTH"
  },
  "chapter": {
    "identifier": "3",
    "text": "LICENSES AND PERMITS"
  },
  "heading": {
    "title": "17",
    "chaptersection": "308",
    "identifier": "17-308",
    "catch_text": "Fees."
  }
}