{
  "text": "The court at any time may correct any defect or informality in any notice, petition, pleading, order or decree in the proceeding, or cause real property affected by such defect, informality or lack of jurisdiction to be excluded therefrom, or other real property affected by such defect, informality or lack of jurisdiction to be included therein by amendment, upon ten days' notice, published and posted as provided for the institution of the proceeding, and may direct such further notices to be given to any party in interest as it shall deem proper. ",
  "sections": [

  ],
  "title": {
    "identifier": "5",
    "text": "BUDGET; CAPITAL PROJECTS"
  },
  "chapter": {
    "identifier": "3",
    "text": "CONDEMNATION PROCEDURES"
  },
  "heading": {
    "title": "5",
    "chaptersection": "331",
    "identifier": "5-331",
    "catch_text": "Correction of defects."
  }
}